README.md
setup.py
carry/__init__.py
carry/bar.py
carry/command.py
carry/dataframe.py
carry/default.py
carry/dispatcher.py
carry/exc.py
carry/logger.py
carry/store.py
carry/task.py
carry/utils.py
carry/version.py
carry.egg-info/PKG-INFO
carry.egg-info/SOURCES.txt
carry.egg-info/dependency_links.txt
carry.egg-info/entry_points.txt
carry.egg-info/requires.txt
carry.egg-info/top_level.txt
carry/dialects/__init__.py
carry/dialects/base.py
carry/dialects/mssql.py
carry/dialects/mysql.py
carry/dialects/oracle.py
carry/dialects/postgres.py
carry/dialects/sqlite.py
carry/transform/__init__.py