Metadata-Version: 1.2
Name: carry
Version: 0.3.1
Summary: Carry is an utility ETL(extract-transform-load) tool
Home-page: https://github.com/toaco/carry
Author: Jeffrey
Author-email: Jeffrey.S.Teo@gmail.com
License: GPL-3.0
Keywords: ETL,extract-transform-load,utility
Platform: any
Classifier: Development Status :: 4 - Beta
Classifier: Intended Audience :: Developers
Classifier: Topic :: Software Development :: Libraries
Classifier: Topic :: Software Development :: Libraries :: Python Modules
Classifier: License :: OSI Approved :: GNU General Public License v3 (GPLv3)
Classifier: Operating System :: OS Independent
Classifier: Programming Language :: Python :: 2
Classifier: Programming Language :: Python :: 2.7
Classifier: Programming Language :: Python :: 3
Classifier: Programming Language :: Python :: 3.5
Classifier: Programming Language :: Python :: 3.6
Requires-Python: >=2.7,!=3.0.*,!=3.1.*,!=3.2.*,!=3.3.*
